ghasedakpack/__init__.py
ghasedakpack/ghasedakpack.py
ghasedakpack-0.1.13.dist-info/LICENSE
ghasedakpack-0.1.13.dist-info/METADATA
ghasedakpack-0.1.13.dist-info/WHEEL
ghasedakpack-0.1.13.dist-info/top_level.txt
ghasedakpack-0.1.13.dist-info/RECORD
