Metadata-Version: 2.1
Name: ghasedakpack
Version: 0.1.13
Summary: Ghasedak sms webservice api wrapper for python.
Home-page: http://github.com/ghasedakapi/ghasedak-python
Author: Ghasedak Group
Author-email: 
Classifier: Programming Language :: Python :: 3
Classifier: License :: OSI Approved :: MIT License
Classifier: Operating System :: OS Independent
License-File: LICENSE
